ctec_utils/Ampq.py
ctec_utils/Database.py
ctec_utils/KafkaHandler.py
ctec_utils/Models.py
ctec_utils/Request.py
ctec_utils/__init__.py
ctec_utils-2.0.data/data/README.rst
ctec_utils-2.0.dist-info/METADATA
ctec_utils-2.0.dist-info/WHEEL
ctec_utils-2.0.dist-info/top_level.txt
ctec_utils-2.0.dist-info/RECORD
