Metadata-Version: 2.1
Name: ctec-utils
Version: 2.0
Summary: working tool
Home-page: http://www.189.cn/
Author: wangjy
Author-email: 1149447019@qq.com
License: Apache License v2
Requires-Dist: msgpack (>=0.5.6)
Requires-Dist: pika (>=0.13.1)
Requires-Dist: requests (>=2.20.0)
Requires-Dist: DBUtils (>=1.3)
Requires-Dist: cx-Oracle (>=7.1.1)
Requires-Dist: redis-py-cluster (>=1.3.4)
Requires-Dist: redis (>=2.10.6)
Requires-Dist: pymongo (>=3.8.0)
Requires-Dist: pymysql (>=0.9.3)
Requires-Dist: six (>=1.12.0)
Requires-Dist: kafka-python (>=1.4.6)
Requires-Dist: logstash-formatter (>=0.5.17)
